ActDeact-1.0.0.dist-info/LICENSE.txt
ActDeact-1.0.0.dist-info/METADATA
ActDeact-1.0.0.dist-info/RECORD
ActDeact-1.0.0.dist-info/WHEEL
ActDeact-1.0.0.dist-info/entry_points.txt
ActDeact-1.0.0.dist-info/top_level.txt
act/__init__.py
actDeact/__init__.py
actDeact/actDeact.conf
deact/__init__.py
