Metadata-Version: 2.1
Name: ActDeact
Version: 1.0.0
Summary: Activate and deactivate config files easily
Home-page: https://github.com/wutzi15/actDeact
Author: Benedikt Bergenthal
Author-email: mail@benedikt-bergenthal.de
License: UNKNOWN
Project-URL: Bug Reports, https://github.com/wutzi15/actDeact/issues
Project-URL: Source, https://github.com/wutzi15/actDeact
Keywords: config configfile Activate deactivate
Platform: UNKNOWN
Classifier: Development Status :: 4 - Beta
Classifier: Intended Audience :: System Administrators
Classifier: Topic :: System :: Systems Administration
Classifier: License :: OSI Approved :: Apache Software License
Classifier: Programming Language :: Python :: 3
Classifier: Programming Language :: Python :: 3.4
Classifier: Programming Language :: Python :: 3.5
Classifier: Programming Language :: Python :: 3.6
Requires-Dist: ConfigParser
